composio/__init__.py
composio/__version__.py
composio/constants.py
composio/exceptions.py
composio/py.typed
composio/cli/__init__.py
composio/cli/__main__.py
composio/cli/actions.py
composio/cli/add.py
composio/cli/apps.py
composio/cli/connections.py
composio/cli/context.py
composio/cli/execute.py
composio/cli/integrations.py
composio/cli/login.py
composio/cli/logout.py
composio/cli/serve.py
composio/cli/triggers.py
composio/cli/whoami.py
composio/cli/utils/__init__.py
composio/cli/utils/decorators.py
composio/cli/utils/helpfulcmd.py
composio/cli/utils/params.py
composio/client/__init__.py
composio/client/base.py
composio/client/collections.py
composio/client/endpoints.py
composio/client/exceptions.py
composio/client/files.py
composio/client/http.py
composio/client/utils.py
composio/client/enums/__init__.py
composio/client/enums/action.py
composio/client/enums/action.pyi
composio/client/enums/app.py
composio/client/enums/app.pyi
composio/client/enums/base.py
composio/client/enums/enum.py
composio/client/enums/tag.py
composio/client/enums/tag.pyi
composio/client/enums/trigger.py
composio/client/enums/trigger.pyi
composio/core/__init__.py
composio/core/cls/__init__.py
composio/core/cls/catch_all_exceptions.py
composio/core/cls/did_you_mean.py
composio/server/__init__.py
composio/server/api.py
composio/storage/__init__.py
composio/storage/base.py
composio/storage/user.py
composio/tools/__init__.py
composio/tools/schema.py
composio/tools/toolset.py
composio/tools/base/__init__.py
composio/tools/base/abs.py
composio/tools/base/exceptions.py
composio/tools/base/local.py
composio/tools/base/runtime.py
composio/tools/env/__init__.py
composio/tools/env/base.py
composio/tools/env/constants.py
composio/tools/env/factory.py
composio/tools/env/history.py
composio/tools/env/id.py
composio/tools/env/browsermanager/__init__.py
composio/tools/env/browsermanager/browser.py
composio/tools/env/browsermanager/manager.py
composio/tools/env/docker/__init__.py
composio_core-0.7.19.dist-info/METADATA
composio_core-0.7.19.dist-info/WHEEL
composio_core-0.7.19.dist-info/entry_points.txt
composio_core-0.7.19.dist-info/top_level.txt
composio_core-0.7.19.dist-info/RECORD
