Metadata-Version: 2.4
Name: composio_core
Version: 0.7.19
Summary: Core package to act as a bridge between composio platform and other services.
Home-page: https://github.com/composiohq/composio
Author: Utkarsh
Author-email: utkarsh@composio.dev
Classifier: Programming Language :: Python :: 3
Classifier: License :: OSI Approved :: Apache Software License
Classifier: Operating System :: OS Independent
Requires-Python: >=3.9,<4
Requires-Dist: aiohttp
Requires-Dist: requests<3,>=2.31.0
Requires-Dist: jsonschema<5,>=4.21.1
Requires-Dist: sentry-sdk>=2.0.0
Requires-Dist: pysher==1.0.8
Requires-Dist: pydantic>=2.6.4
Requires-Dist: importlib-metadata>=4.8.1
Requires-Dist: jsonref>=1.1.0
Requires-Dist: inflection>=0.5.1
Requires-Dist: semver>=2.13.0
Requires-Dist: click
Requires-Dist: rich<14,>=13.7.1
Requires-Dist: pyperclip<2,>=1.8.2
Requires-Dist: Pillow<11,>=10.2.0
Requires-Dist: paramiko>=3.4.1
Requires-Dist: fastapi
Requires-Dist: uvicorn
Requires-Dist: pyyaml>=6.0.2
Provides-Extra: all
Requires-Dist: aiohttp; extra == "all"
Requires-Dist: requests<3,>=2.31.0; extra == "all"
Requires-Dist: jsonschema<5,>=4.21.1; extra == "all"
Requires-Dist: sentry-sdk>=2.0.0; extra == "all"
Requires-Dist: pysher==1.0.8; extra == "all"
Requires-Dist: pydantic>=2.6.4; extra == "all"
Requires-Dist: importlib-metadata>=4.8.1; extra == "all"
Requires-Dist: jsonref>=1.1.0; extra == "all"
Requires-Dist: inflection>=0.5.1; extra == "all"
Requires-Dist: semver>=2.13.0; extra == "all"
Requires-Dist: click; extra == "all"
Requires-Dist: rich<14,>=13.7.1; extra == "all"
Requires-Dist: pyperclip<2,>=1.8.2; extra == "all"
Requires-Dist: Pillow<11,>=10.2.0; extra == "all"
Requires-Dist: paramiko>=3.4.1; extra == "all"
Requires-Dist: fastapi; extra == "all"
Requires-Dist: uvicorn; extra == "all"
Requires-Dist: pyyaml>=6.0.2; extra == "all"
Requires-Dist: e2b<1.1.0,>=0.17.2a37; extra == "all"
Requires-Dist: e2b-code-interpreter; extra == "all"
Requires-Dist: docker>=7.1.0; extra == "all"
Requires-Dist: gql; extra == "all"
Requires-Dist: requests_toolbelt; extra == "all"
Requires-Dist: pygments; extra == "all"
Requires-Dist: pathspec; extra == "all"
Requires-Dist: diskcache; extra == "all"
Requires-Dist: networkx; extra == "all"
Requires-Dist: ruff; extra == "all"
Requires-Dist: flake8; extra == "all"
Requires-Dist: transformers; extra == "all"
Provides-Extra: tools
Requires-Dist: pygments; extra == "tools"
Requires-Dist: pathspec; extra == "tools"
Requires-Dist: diskcache; extra == "tools"
Requires-Dist: networkx; extra == "tools"
Requires-Dist: ruff; extra == "tools"
Requires-Dist: flake8; extra == "tools"
Requires-Dist: transformers; extra == "tools"
Provides-Extra: e2b
Requires-Dist: e2b<1.1.0,>=0.17.2a37; extra == "e2b"
Requires-Dist: e2b-code-interpreter; extra == "e2b"
Provides-Extra: flyio
Requires-Dist: gql; extra == "flyio"
Requires-Dist: requests_toolbelt; extra == "flyio"
Provides-Extra: docker
Requires-Dist: docker>=7.1.0; extra == "docker"
Dynamic: author
Dynamic: author-email
Dynamic: classifier
Dynamic: description
Dynamic: description-content-type
Dynamic: home-page
Dynamic: provides-extra
Dynamic: requires-dist
Dynamic: requires-python
Dynamic: summary
